odoo10_addon_project_double_alias-10.0.1.0.1-py2.7-nspkg.pth
odoo/addons/project_double_alias/README.rst
odoo/addons/project_double_alias/__init__.py
odoo/addons/project_double_alias/__manifest__.py
odoo/addons/project_double_alias/hooks.py
odoo/addons/project_double_alias/i18n/de.po
odoo/addons/project_double_alias/i18n/es.po
odoo/addons/project_double_alias/i18n/es_MX.po
odoo/addons/project_double_alias/i18n/fi.po
odoo/addons/project_double_alias/i18n/fr.po
odoo/addons/project_double_alias/i18n/hr.po
odoo/addons/project_double_alias/i18n/nl.po
odoo/addons/project_double_alias/i18n/nl_NL.po
odoo/addons/project_double_alias/i18n/pt.po
odoo/addons/project_double_alias/i18n/pt_BR.po
odoo/addons/project_double_alias/i18n/pt_PT.po
odoo/addons/project_double_alias/i18n/sl.po
odoo/addons/project_double_alias/i18n/tr.po
odoo/addons/project_double_alias/i18n/zh_CN.po
odoo/addons/project_double_alias/models/__init__.py
odoo/addons/project_double_alias/models/mail_alias.py
odoo/addons/project_double_alias/models/project_issue.py
odoo/addons/project_double_alias/models/project_project.py
odoo/addons/project_double_alias/models/project_task.py
odoo/addons/project_double_alias/static/description/icon.png
odoo/addons/project_double_alias/static/description/icon.svg
odoo/addons/project_double_alias/tests/__init__.py
odoo/addons/project_double_alias/tests/test_project_double_alias.py
odoo/addons/project_double_alias/views/project_project_view.xml
odoo10_addon_project_double_alias-10.0.1.0.1.dist-info/DESCRIPTION.rst
odoo10_addon_project_double_alias-10.0.1.0.1.dist-info/METADATA
odoo10_addon_project_double_alias-10.0.1.0.1.dist-info/RECORD
odoo10_addon_project_double_alias-10.0.1.0.1.dist-info/WHEEL
odoo10_addon_project_double_alias-10.0.1.0.1.dist-info/metadata.json
odoo10_addon_project_double_alias-10.0.1.0.1.dist-info/namespace_packages.txt
odoo10_addon_project_double_alias-10.0.1.0.1.dist-info/top_level.txt
