Metadata-Version: 2.0
Name: odoo10-addon-project-double-alias
Version: 10.0.1.0.1
Summary: Define an alias for tasks and another alias for issues
Home-page: https://www.tecnativa.com/
Author: Tecnativa, Odoo Community Association (OCA)
Author-email: support@odoo-community.org
License: AGPL-3
Platform: UNKNOWN
Classifier: Programming Language :: Python :: 2.7
Classifier: Framework :: Odoo
Classifier: License :: OSI Approved :: GNU Affero General Public License v3
Requires-Dist: odoo (<10.1dev,>=10.0)
